<?xml version="1.0"?>
<Runs Version="1" Minor="0">
	<Run Id="PWM_processing_system7_0_0_synth_1" LaunchDir="D:/Project/Wireless Charge PWM/PWM/PWM.runs/PWM_processing_system7_0_0_synth_1" FlowId="Vivado_Synthesis" FromStepId="vivado" ToStepId="vivado"/>
	<Run Id="PWM_PWM_module_0_0_synth_1" LaunchDir="D:/Project/Wireless Charge PWM/PWM/PWM.runs/PWM_PWM_module_0_0_synth_1" FlowId="Vivado_Synthesis" FromStepId="vivado" ToStepId="vivado"/>
	<Run Id="PWM_rst_ps7_0_200M_1_synth_1" LaunchDir="D:/Project/Wireless Charge PWM/PWM/PWM.runs/PWM_rst_ps7_0_200M_1_synth_1" FlowId="Vivado_Synthesis" FromStepId="vivado" ToStepId="vivado"/>
	<Run Id="PWM_key_debounce_0_3_synth_1" LaunchDir="D:/Project/Wireless Charge PWM/PWM/PWM.runs/PWM_key_debounce_0_3_synth_1" FlowId="Vivado_Synthesis" FromStepId="vivado" ToStepId="vivado"/>
	<Run Id="PWM_COM_IP_0_1_synth_1" LaunchDir="D:/Project/Wireless Charge PWM/PWM/PWM.runs/PWM_COM_IP_0_1_synth_1" FlowId="Vivado_Synthesis" FromStepId="vivado" ToStepId="vivado"/>
	<Run Id="PWM_auto_pc_0_synth_1" LaunchDir="D:/Project/Wireless Charge PWM/PWM/PWM.runs/PWM_auto_pc_0_synth_1" FlowId="Vivado_Synthesis" FromStepId="vivado" ToStepId="vivado"/>
	<Parameters>
		<Parameter Name="runs.monitorLSFJobs" Val="true" Type="bool"/>
		<Parameter Name="runs.enableClusterConf" Val="true" Type="bool"/>
	</Parameters>
</Runs>

